[
  {
    "platform" : "IPHONE",
    "searchTime" : "2022-01-23T02:32:23.513Z[UTC]",
    "searchQuery" : "man ",
    "searchInteractionURIs" : [
      "spotify:album:2S8AWAM0nxyFy66YnUfIs3"
    ]
  },
  {
    "platform" : "IPHONE",
    "searchTime" : "2022-01-24T17:54:13.213Z[UTC]",
    "searchQuery" : "rado",
    "searchInteractionURIs" : [
      "spotify:artist:4Z8W4fKeB5YxbusRsdQVPb"
    ]
  },
  {
    "platform" : "IPHONE",
    "searchTime" : "2022-01-24T17:54:14.484Z[UTC]",
    "searchQuery" : "radio",
    "searchInteractionURIs" : [
    ]
  },
  {
    "platform" : "IPHONE",
    "searchTime" : "2022-01-24T22:54:10.051Z[UTC]",
    "searchQuery" : "tame",
    "searchInteractionURIs" : [
      "spotify:artist:5INjqkS1o8h1imAzPqGZBb"
    ]
  },
  {
    "platform" : "IPHONE",
    "searchTime" : "2022-01-26T21:50:24.875Z[UTC]",
    "searchQuery" : "strings of ",
    "searchInteractionURIs" : [
      "spotify:track:7N3FfUFMud1rjI6Vgw71mm",
      "spotify:track:7N3FfUFMud1rjI6Vgw71mm"
    ]
  },
  {
    "platform" : "IPHONE",
    "searchTime" : "2022-01-28T06:00:06.052Z[UTC]",
    "searchQuery" : "danza k",
    "searchInteractionURIs" : [
      "spotify:track:28fW93JrXrZjbSKKpqXsDc"
    ]
  },
  {
    "platform" : "IPHONE",
    "searchTime" : "2022-01-28T06:02:28.514Z[UTC]",
    "searchQuery" : "kay tlock",
    "searchInteractionURIs" : [
    ]
  },
  {
    "platform" : "IPHONE",
    "searchTime" : "2022-01-28T06:03:05.367Z[UTC]",
    "searchQuery" : "a ta",
    "searchInteractionURIs" : [
      "spotify:track:52A8OAP8lTQKZCj4Rce92B"
    ]
  },
  {
    "platform" : "IPHONE",
    "searchTime" : "2022-01-29T21:28:49.587Z[UTC]",
    "searchQuery" : "haunted",
    "searchInteractionURIs" : [
      "spotify:track:1toNKayLMeCcVlsLGXJl7n"
    ]
  },
  {
    "platform" : "IPHONE",
    "searchTime" : "2022-01-31T01:26:19.577Z[UTC]",
    "searchQuery" : "laura",
    "searchInteractionURIs" : [
      "spotify:artist:3sklFG9fuDAq3vbIZlkNH6"
    ]
  },
  {
    "platform" : "IPHONE",
    "searchTime" : "2022-01-31T02:02:23.146Z[UTC]",
    "searchQuery" : "hold",
    "searchInteractionURIs" : [
      "spotify:track:5nIu0VwPOsjkF61zfevLKh"
    ]
  },
  {
    "platform" : "IPHONE",
    "searchTime" : "2022-02-05T03:35:39.231Z[UTC]",
    "searchQuery" : "shoreline ",
    "searchInteractionURIs" : [
      "spotify:artist:4tYSBptyGeVyZsk8JC4JHZ"
    ]
  },
  {
    "platform" : "IPHONE",
    "searchTime" : "2022-02-05T03:58:53.123Z[UTC]",
    "searchQuery" : "yea",
    "searchInteractionURIs" : [
      "spotify:artist:3qiHUAX7zY4Qnjx8TNUzVx"
    ]
  },
  {
    "platform" : "IPHONE",
    "searchTime" : "2022-02-05T22:40:01.273Z[UTC]",
    "searchQuery" : "stop ",
    "searchInteractionURIs" : [
      "spotify:track:2lLG56qpLP3UbcLuzMvkWX"
    ]
  },
  {
    "platform" : "IPHONE",
    "searchTime" : "2022-02-12T21:49:29Z[UTC]",
    "searchQuery" : "thox",
    "searchInteractionURIs" : [
      "spotify:artist:1O8X4zxUh4AdAPFttOTlLr"
    ]
  },
  {
    "platform" : "IPHONE",
    "searchTime" : "2022-02-13T04:18:54.021Z[UTC]",
    "searchQuery" : "ds",
    "searchInteractionURIs" : [
      "spotify:album:02uWB8Kekadkl3yGBoOOcx"
    ]
  },
  {
    "platform" : "IPHONE",
    "searchTime" : "2022-02-13T17:36:44.938Z[UTC]",
    "searchQuery" : "we",
    "searchInteractionURIs" : [
      "spotify:artist:1Xyo4u8uXC1ZmMpatF05PJ"
    ]
  },
  {
    "platform" : "IPHONE",
    "searchTime" : "2022-02-13T20:06:44.890Z[UTC]",
    "searchQuery" : "ye",
    "searchInteractionURIs" : [
      "spotify:artist:3qiHUAX7zY4Qnjx8TNUzVx"
    ]
  },
  {
    "platform" : "IPHONE",
    "searchTime" : "2022-02-13T21:21:35.315Z[UTC]",
    "searchQuery" : "yung lean",
    "searchInteractionURIs" : [
      "spotify:artist:67lytN32YpUxiSeWlKfHJ3"
    ]
  },
  {
    "platform" : "IPHONE",
    "searchTime" : "2022-02-15T06:10:03.391Z[UTC]",
    "searchQuery" : "weekend",
    "searchInteractionURIs" : [
      "spotify:artist:1Xyo4u8uXC1ZmMpatF05PJ"
    ]
  },
  {
    "platform" : "IPHONE",
    "searchTime" : "2022-02-18T05:58:03.865Z[UTC]",
    "searchQuery" : "yeat",
    "searchInteractionURIs" : [
      "spotify:artist:3qiHUAX7zY4Qnjx8TNUzVx"
    ]
  },
  {
    "platform" : "IPHONE",
    "searchTime" : "2022-02-21T01:18:46.012Z[UTC]",
    "searchQuery" : "the darnkess ",
    "searchInteractionURIs" : [
      "spotify:track:4ahFzFAZRpfWaGbA2J3dAq"
    ]
  },
  {
    "platform" : "IPHONE",
    "searchTime" : "2022-02-23T15:51:24.350Z[UTC]",
    "searchQuery" : "do i look ",
    "searchInteractionURIs" : [
      "spotify:episode:3Jgyw1XD1Kk1qOONfZOwBz"
    ]
  },
  {
    "platform" : "IPHONE",
    "searchTime" : "2022-02-24T01:12:24.088Z[UTC]",
    "searchQuery" : "civiliza",
    "searchInteractionURIs" : [
    ]
  },
  {
    "platform" : "IPHONE",
    "searchTime" : "2022-02-24T01:12:46.698Z[UTC]",
    "searchQuery" : "snivi",
    "searchInteractionURIs" : [
      "spotify:album:2biXiNkJXdREKZwx4HrhZE"
    ]
  },
  {
    "platform" : "IPHONE",
    "searchTime" : "2022-02-26T00:48:05.250Z[UTC]",
    "searchQuery" : "top",
    "searchInteractionURIs" : [
      "spotify:track:55Q46o5adtSobImSKrrlqW"
    ]
  },
  {
    "platform" : "IPHONE",
    "searchTime" : "2022-02-27T04:28:16.880Z[UTC]",
    "searchQuery" : "pete did",
    "searchInteractionURIs" : [
      "spotify:user:12101827207"
    ]
  },
  {
    "platform" : "IPHONE",
    "searchTime" : "2022-02-27T04:28:40.146Z[UTC]",
    "searchQuery" : "p diddy",
    "searchInteractionURIs" : [
      "spotify:artist:59wfkuBoNyhDMQGCljbUbA"
    ]
  },
  {
    "platform" : "IPHONE",
    "searchTime" : "2022-02-27T04:45:03.772Z[UTC]",
    "searchQuery" : "weekend",
    "searchInteractionURIs" : [
      "spotify:artist:1Xyo4u8uXC1ZmMpatF05PJ"
    ]
  },
  {
    "platform" : "IPHONE",
    "searchTime" : "2022-02-27T04:45:11.984Z[UTC]",
    "searchQuery" : "blind",
    "searchInteractionURIs" : [
      "spotify:track:0VjIjW4GlUZAMYd2vXMi3b"
    ]
  },
  {
    "platform" : "IPHONE",
    "searchTime" : "2022-02-27T19:12:30.205Z[UTC]",
    "searchQuery" : "gucci",
    "searchInteractionURIs" : [
      "spotify:artist:13y7CgLHjMVRMDqxdx0Xdo"
    ]
  },
  {
    "platform" : "IPHONE",
    "searchTime" : "2022-03-13T01:39:29.878Z[UTC]",
    "searchQuery" : "ken ca",
    "searchInteractionURIs" : [
      "spotify:artist:3gBZUcNeVumkeeJ19CY2sX"
    ]
  },
  {
    "platform" : "IPHONE",
    "searchTime" : "2022-03-13T15:58:51.478Z[UTC]",
    "searchQuery" : "father ",
    "searchInteractionURIs" : [
      "spotify:track:4KW1lqgSr8TKrvBII0Brf8",
      "spotify:track:4KW1lqgSr8TKrvBII0Brf8",
      "spotify:track:1Wsbr1d2BouNGk2q92mIj7"
    ]
  },
  {
    "platform" : "IPHONE",
    "searchTime" : "2022-03-15T01:56:29.394Z[UTC]",
    "searchQuery" : "ds2",
    "searchInteractionURIs" : [
      "spotify:album:0fUy6IdLHDpGNwavIlhEsl"
    ]
  },
  {
    "platform" : "IPHONE",
    "searchTime" : "2022-03-15T13:08:49.315Z[UTC]",
    "searchQuery" : "lion k",
    "searchInteractionURIs" : [
      "spotify:album:3YA5DdB3wSz4pdfEXoMyRd"
    ]
  },
  {
    "platform" : "IPHONE",
    "searchTime" : "2022-03-15T13:42:42.340Z[UTC]",
    "searchQuery" : "mbd",
    "searchInteractionURIs" : [
      "spotify:album:20r762YmB5HeofjMCiPMLv"
    ]
  },
  {
    "platform" : "IPHONE",
    "searchTime" : "2022-03-15T14:03:33.736Z[UTC]",
    "searchQuery" : "i am ironman",
    "searchInteractionURIs" : [
    ]
  },
  {
    "platform" : "IPHONE",
    "searchTime" : "2022-03-15T14:04:09.998Z[UTC]",
    "searchQuery" : "iron",
    "searchInteractionURIs" : [
      "spotify:track:4svkPL62HbvyFgf0nHFXAF"
    ]
  },
  {
    "platform" : "IPHONE",
    "searchTime" : "2022-03-15T14:06:12.773Z[UTC]",
    "searchQuery" : "making you c",
    "searchInteractionURIs" : [
      "spotify:track:1ug52CZX2B0VdnFtNKS1gH"
    ]
  },
  {
    "platform" : "IPHONE",
    "searchTime" : "2022-03-15T14:15:26.514Z[UTC]",
    "searchQuery" : "life k",
    "searchInteractionURIs" : [
      "spotify:album:7gsWAHLeT0w7es6FofOXk1"
    ]
  },
  {
    "platform" : "IPHONE",
    "searchTime" : "2022-03-15T14:16:55.840Z[UTC]",
    "searchQuery" : "callin",
    "searchInteractionURIs" : [
      "spotify:track:4POTimapPaHCx09j8xW4qK",
      "spotify:track:4POTimapPaHCx09j8xW4qK"
    ]
  },
  {
    "platform" : "IPHONE",
    "searchTime" : "2022-03-15T15:18:53.052Z[UTC]",
    "searchQuery" : "leviath",
    "searchInteractionURIs" : [
      "spotify:artist:6CJU2RwwB10D0KoYYqWYeM",
      "spotify:track:5oZvmo8ARpuBbaGArm8cBn"
    ]
  },
  {
    "platform" : "IPHONE",
    "searchTime" : "2022-03-15T15:22:51.699Z[UTC]",
    "searchQuery" : "ult",
    "searchInteractionURIs" : [
      "spotify:track:5BSz8sJO2YmKfNVQG7fq2J",
      "spotify:track:1eQBEelI2NCy7AUTerX0KS"
    ]
  },
  {
    "platform" : "IPHONE",
    "searchTime" : "2022-03-15T15:25:51.873Z[UTC]",
    "searchQuery" : "xscape",
    "searchInteractionURIs" : [
      "spotify:track:0jNFDcGAXPs5ahngmD5R6n"
    ]
  },
  {
    "platform" : "IPHONE",
    "searchTime" : "2022-03-15T15:26:01.382Z[UTC]",
    "searchQuery" : "x",
    "searchInteractionURIs" : [
      "spotify:track:6fwdbPMwP1zVStm8FybmkO"
    ]
  },
  {
    "platform" : "IPHONE",
    "searchTime" : "2022-03-15T15:26:20.859Z[UTC]",
    "searchQuery" : "g herb",
    "searchInteractionURIs" : [
      "spotify:artist:5QdEbQJ3ylBnc3gsIASAT5"
    ]
  },
  {
    "platform" : "IPHONE",
    "searchTime" : "2022-03-15T15:26:22.088Z[UTC]",
    "searchQuery" : "g herbo",
    "searchInteractionURIs" : [
    ]
  },
  {
    "platform" : "IPHONE",
    "searchTime" : "2022-03-15T15:27:11.313Z[UTC]",
    "searchQuery" : "xscape",
    "searchInteractionURIs" : [
      "spotify:track:0jNFDcGAXPs5ahngmD5R6n"
    ]
  },
  {
    "platform" : "IPHONE",
    "searchTime" : "2022-03-15T15:27:49.670Z[UTC]",
    "searchQuery" : "x",
    "searchInteractionURIs" : [
      "spotify:track:6fwdbPMwP1zVStm8FybmkO",
      "spotify:track:6fwdbPMwP1zVStm8FybmkO",
      "spotify:track:6fwdbPMwP1zVStm8FybmkO"
    ]
  },
  {
    "platform" : "IPHONE",
    "searchTime" : "2022-03-15T15:28:47.232Z[UTC]",
    "searchQuery" : "xacape",
    "searchInteractionURIs" : [
      "spotify:track:0jNFDcGAXPs5ahngmD5R6n"
    ]
  },
  {
    "platform" : "IPHONE",
    "searchTime" : "2022-03-15T15:29:12.449Z[UTC]",
    "searchQuery" : "rock an",
    "searchInteractionURIs" : [
      "spotify:track:1V0jEAE4UreyX8KYxGLnLP"
    ]
  },
  {
    "platform" : "IPHONE",
    "searchTime" : "2022-03-15T15:30:06.192Z[UTC]",
    "searchQuery" : "evil eye",
    "searchInteractionURIs" : [
      "spotify:track:01Ju1igrEJny08Y27Ou5wF"
    ]
  },
  {
    "platform" : "IPHONE",
    "searchTime" : "2022-03-15T15:30:34.720Z[UTC]",
    "searchQuery" : "night lovl",
    "searchInteractionURIs" : [
      "spotify:artist:2y246nnP9pQT0E6v3ZMMOO"
    ]
  },
  {
    "platform" : "IPHONE",
    "searchTime" : "2022-03-15T15:30:51.602Z[UTC]",
    "searchQuery" : "oh my dis",
    "searchInteractionURIs" : [
      "spotify:track:2rMFawCg4BW65jzbwztXAV"
    ]
  },
  {
    "platform" : "IPHONE",
    "searchTime" : "2022-03-15T15:31:07.573Z[UTC]",
    "searchQuery" : "whnna",
    "searchInteractionURIs" : [
    ]
  },
  {
    "platform" : "IPHONE",
    "searchTime" : "2022-03-15T15:31:10.868Z[UTC]",
    "searchQuery" : "nastu girl",
    "searchInteractionURIs" : [
      "spotify:track:2f8y4CuG57UJEmkG3ujd0D"
    ]
  },
  {
    "platform" : "IPHONE",
    "searchTime" : "2022-03-16T05:06:01.313Z[UTC]",
    "searchQuery" : "super  o",
    "searchInteractionURIs" : [
      "spotify:track:3sjtQ07ptlPzw2N4YmGW3S"
    ]
  },
  {
    "platform" : "IPHONE",
    "searchTime" : "2022-03-21T06:28:05.127Z[UTC]",
    "searchQuery" : "no more ",
    "searchInteractionURIs" : [
      "spotify:track:0zLClc0emc6qUeV1p5nc99"
    ]
  },
  {
    "platform" : "IPHONE",
    "searchTime" : "2022-03-23T22:46:24.324Z[UTC]",
    "searchQuery" : "runaw",
    "searchInteractionURIs" : [
      "spotify:track:3DK6m7It6Pw857FcQftMds"
    ]
  },
  {
    "platform" : "IPHONE",
    "searchTime" : "2022-03-24T03:14:11.263Z[UTC]",
    "searchQuery" : "future ",
    "searchInteractionURIs" : [
      "spotify:artist:1RyvyyTE3xzB2ZywiAwp0i"
    ]
  },
  {
    "platform" : "IPHONE",
    "searchTime" : "2022-03-26T01:10:07.343Z[UTC]",
    "searchQuery" : "h",
    "searchInteractionURIs" : [
      "spotify:track:3USxtqRwSYz57Ewm6wWRMp"
    ]
  },
  {
    "platform" : "IPHONE",
    "searchTime" : "2022-03-26T01:24:05.715Z[UTC]",
    "searchQuery" : "al capone",
    "searchInteractionURIs" : [
    ]
  },
  {
    "platform" : "IPHONE",
    "searchTime" : "2022-03-26T21:24:03.480Z[UTC]",
    "searchQuery" : "high sch",
    "searchInteractionURIs" : [
      "spotify:playlist:6B74kB13ky4k8RVGQSbSUl",
      "spotify:album:6j8k5gIeWzXapGKTVaZzER"
    ]
  },
  {
    "platform" : "IPHONE",
    "searchTime" : "2022-03-29T16:29:29.379Z[UTC]",
    "searchQuery" : "fuck",
    "searchInteractionURIs" : [
      "spotify:track:49zD0wr2S3d0lZPib0K4e1"
    ]
  },
  {
    "platform" : "IPHONE",
    "searchTime" : "2022-03-31T17:20:45.346Z[UTC]",
    "searchQuery" : "baby sm",
    "searchInteractionURIs" : [
      "spotify:artist:15oLsNy8mZYaIukh4eDhXy"
    ]
  },
  {
    "platform" : "IPHONE",
    "searchTime" : "2022-04-01T02:14:56.249Z[UTC]",
    "searchQuery" : "tee",
    "searchInteractionURIs" : [
      "spotify:track:5uYqmEN6TAAE8ss8YmprNV"
    ]
  },
  {
    "platform" : "IPHONE",
    "searchTime" : "2022-04-01T23:59:25.259Z[UTC]",
    "searchQuery" : "yeat",
    "searchInteractionURIs" : [
      "spotify:artist:3qiHUAX7zY4Qnjx8TNUzVx"
    ]
  },
  {
    "platform" : "IPHONE",
    "searchTime" : "2022-04-02T00:07:30.764Z[UTC]",
    "searchQuery" : "300",
    "searchInteractionURIs" : [
      "spotify:track:2ZltjIqztEpZtafc8w0I9t"
    ]
  },
  {
    "platform" : "IPHONE",
    "searchTime" : "2022-04-03T04:16:08.469Z[UTC]",
    "searchQuery" : "future",
    "searchInteractionURIs" : [
      "spotify:artist:1RyvyyTE3xzB2ZywiAwp0i"
    ]
  },
  {
    "platform" : "IPHONE",
    "searchTime" : "2022-04-03T19:24:15.931Z[UTC]",
    "searchQuery" : "weeken",
    "searchInteractionURIs" : [
      "spotify:artist:1Xyo4u8uXC1ZmMpatF05PJ"
    ]
  },
  {
    "platform" : "IPHONE",
    "searchTime" : "2022-04-03T21:06:14.419Z[UTC]",
    "searchQuery" : "latt",
    "searchInteractionURIs" : [
      "spotify:artist:3MdXrJWsbVzdn6fe5JYkSQ"
    ]
  },
  {
    "platform" : "IPHONE",
    "searchTime" : "2022-04-05T19:25:16.675Z[UTC]",
    "searchQuery" : "lik baby",
    "searchInteractionURIs" : [
      "spotify:track:1MGWgLxUXDodD8Tw8TFppN"
    ]
  },
  {
    "platform" : "IPHONE",
    "searchTime" : "2022-04-06T01:17:13.039Z[UTC]",
    "searchQuery" : "chrck",
    "searchInteractionURIs" : [
      "spotify:track:1jk9c0gZI0wbn5GvAj7PBV"
    ]
  },
  {
    "platform" : "IPHONE",
    "searchTime" : "2022-04-06T02:42:05.524Z[UTC]",
    "searchQuery" : "mitski",
    "searchInteractionURIs" : [
      "spotify:artist:2uYWxilOVlUdk4oV9DvwqK"
    ]
  },
  {
    "platform" : "IPHONE",
    "searchTime" : "2022-04-07T18:22:49.451Z[UTC]",
    "searchQuery" : "gucc",
    "searchInteractionURIs" : [
      "spotify:artist:13y7CgLHjMVRMDqxdx0Xdo"
    ]
  },
  {
    "platform" : "IPHONE",
    "searchTime" : "2022-04-09T01:51:41.694Z[UTC]",
    "searchQuery" : "young n",
    "searchInteractionURIs" : [
      "spotify:artist:5yPzzu25VzEk8qrGTLIrE1"
    ]
  },
  {
    "platform" : "IPHONE",
    "searchTime" : "2022-04-09T01:56:16.179Z[UTC]",
    "searchQuery" : "straw",
    "searchInteractionURIs" : [
      "spotify:track:4lAQfuREAHG8IC0PiiigBt"
    ]
  },
  {
    "platform" : "IPHONE",
    "searchTime" : "2022-04-09T01:57:30.408Z[UTC]",
    "searchQuery" : "young ",
    "searchInteractionURIs" : [
      "spotify:artist:50co4Is1HCEo8bhOyUWKpn"
    ]
  },
  {
    "platform" : "IPHONE",
    "searchTime" : "2022-04-09T01:57:37.644Z[UTC]",
    "searchQuery" : "young nudy",
    "searchInteractionURIs" : [
      "spotify:artist:5yPzzu25VzEk8qrGTLIrE1"
    ]
  },
  {
    "platform" : "IPHONE",
    "searchTime" : "2022-04-09T02:02:30.101Z[UTC]",
    "searchQuery" : "yeat",
    "searchInteractionURIs" : [
      "spotify:album:0345WPzPBSeISh2IpIQWxT"
    ]
  },
  {
    "platform" : "IPHONE",
    "searchTime" : "2022-04-10T08:11:59.320Z[UTC]",
    "searchQuery" : "nocap",
    "searchInteractionURIs" : [
      "spotify:artist:4PNHuWkk4ee6R8WEhFVPf5"
    ]
  },
  {
    "platform" : "IPHONE",
    "searchTime" : "2022-04-12T16:57:40.765Z[UTC]",
    "searchQuery" : "young nudy",
    "searchInteractionURIs" : [
      "spotify:artist:5yPzzu25VzEk8qrGTLIrE1"
    ]
  },
  {
    "platform" : "IPHONE",
    "searchTime" : "2022-04-13T04:52:14.631Z[UTC]",
    "searchQuery" : "kis",
    "searchInteractionURIs" : [
      "spotify:track:2q4rjDy9WhaN3o9MvDbO21"
    ]
  },
  {
    "platform" : "IPHONE",
    "searchTime" : "2022-04-13T17:41:18.690Z[UTC]",
    "searchQuery" : "wlr",
    "searchInteractionURIs" : [
      "spotify:album:2QRedhP5RmKJiJ1i8VgDGR"
    ]
  },
  {
    "platform" : "IPHONE",
    "searchTime" : "2022-04-14T17:14:59.997Z[UTC]",
    "searchQuery" : "week",
    "searchInteractionURIs" : [
      "spotify:artist:1Xyo4u8uXC1ZmMpatF05PJ"
    ]
  },
  {
    "platform" : "IPHONE",
    "searchTime" : "2022-04-15T17:04:11.812Z[UTC]",
    "searchQuery" : "yeezus",
    "searchInteractionURIs" : [
      "spotify:album:7D2NdGvBHIavgLhmcwhluK"
    ]
  },
  {
    "platform" : "IPHONE",
    "searchTime" : "2022-04-15T22:31:20.201Z[UTC]",
    "searchQuery" : "dearh",
    "searchInteractionURIs" : [
      "spotify:artist:5RADpgYLOuS2ZxDq7ggYYH"
    ]
  },
  {
    "platform" : "IPHONE",
    "searchTime" : "2022-04-15T22:33:35.083Z[UTC]",
    "searchQuery" : "no sur",
    "searchInteractionURIs" : [
      "spotify:track:10nyNJ6zNy2YVYLrcwLccB",
      "spotify:track:10nyNJ6zNy2YVYLrcwLccB"
    ]
  },
  {
    "platform" : "IPHONE",
    "searchTime" : "2022-04-15T22:34:23.509Z[UTC]",
    "searchQuery" : "weird ",
    "searchInteractionURIs" : [
      "spotify:track:4wajJ1o7jWIg62YqpkHC7S"
    ]
  },
  {
    "platform" : "IPHONE",
    "searchTime" : "2022-04-16T00:15:29.446Z[UTC]",
    "searchQuery" : "hell of",
    "searchInteractionURIs" : [
      "spotify:track:3rCNmRonlHN1TXQLcG3dSk"
    ]
  },
  {
    "platform" : "IPHONE",
    "searchTime" : "2022-04-16T05:03:11.422Z[UTC]",
    "searchQuery" : "h",
    "searchInteractionURIs" : [
    ]
  },
  {
    "platform" : "IPHONE",
    "searchTime" : "2022-04-16T05:04:07.506Z[UTC]",
    "searchQuery" : "tam",
    "searchInteractionURIs" : [
      "spotify:artist:5INjqkS1o8h1imAzPqGZBb"
    ]
  },
  {
    "platform" : "IPHONE",
    "searchTime" : "2022-04-16T05:07:13.485Z[UTC]",
    "searchQuery" : "t",
    "searchInteractionURIs" : [
      "spotify:artist:4V8LLVI7PbaPR0K2TGSxFF"
    ]
  }
]